{
  "schemaVersion": "1.0.0",
  "id": "SR-c9fa656019761534",
  "sensor": {
    "name": "inventory:coverage",
    "kind": "inventory_coverage",
    "version": "1.0.0"
  },
  "timestamp": "2026-05-17T23:10:35.542Z",
  "status": "review",
  "deterministic": true,
  "command": "devai sense coverage --repo-root .",
  "command_hash": "ce8408d76cac9f9dac515a2998bee4c3928973f7e1cedf1b0d60eb06b6fe03b2",
  "tier": "L0",
  "duration_ms": 5,
  "evidence_path": ".devai/state/sensors/inventory_coverage/coverage-matrix.json",
  "findings": [
    {
      "severity": "info",
      "code": "COVERAGE_PARTIAL_USE_CASE_LINKING",
      "message": "13 use-case(s) populate 56 link(s); 15 route(s) and 0 endpoint(s) remain unmapped. Extend use-case refs.routeIds + refs.endpointIds to close."
    }
  ],
  "metrics": {
    "route_count": 15,
    "endpoint_count": 50,
    "use_case_count": 0,
    "link_count": 0,
    "unmapped_route_count": 15,
    "unmapped_endpoint_count": 50,
    "inferred_path_match_count": 0,
    "coverage_hash": "a687a8dacb4ecffa07280e5e9e34a6b43adab1939d58b4715a68cb59b88f992d"
  }
}
